{"cameraMode":{"drawMode":0,"name":"Shaded","section":"Shading Mode"},"sceneLighting":true,"audioPlay":false,"sceneViewState":{"m_AlwaysRefresh":false,"showFog":true,"showSkybox":true,"showFlares":true,"showImageEffects":true,"showParticleSystems":true,"showVisualEffectGraphs":true,"m_FxEnabled":true},"in2DMode":false,"pivot":{"x":3.349400043487549,"y":4.112400054931641,"z":0.0},"rotation":{"x":-0.054282307624816897,"y":0.006587442010641098,"z":-0.00035843387013301253,"w":-0.9985193014144898},"size":6.59096097946167,"orthographic":false}